setup.py
turbo_api_test/__init__.py
turbo_api_test/util.py
turbo_api_test.egg-info/PKG-INFO
turbo_api_test.egg-info/SOURCES.txt
turbo_api_test.egg-info/dependency_links.txt
turbo_api_test.egg-info/pbr.json
turbo_api_test.egg-info/requires.txt
turbo_api_test.egg-info/top_level.txt