Metadata-Version: 1.0
Name: turbo-api-test
Version: 0.0.1
Summary: Turbo_api_test is a framework/tool for api test
Home-page: http://github.com/wecatch/turbo-api-test
Author: Wecatch.me
Author-email: wecatch.me@gmail.com
License: http://www.apache.org/licenses/LICENSE-2.0
Platform: UNKNOWN
